setup.py
sldghmmr4nut/__init__.py
sldghmmr4nut/txt.py
sldghmmr4nut.egg-info/PKG-INFO
sldghmmr4nut.egg-info/SOURCES.txt
sldghmmr4nut.egg-info/dependency_links.txt
sldghmmr4nut.egg-info/top_level.txt
sldghmmr4nut/cmmn/__init__.py
sldghmmr4nut/cmmn/utils.py
sldghmmr4nut/img/__init__.py
sldghmmr4nut/img/convert.py
sldghmmr4nut/lines/__init__.py
sldghmmr4nut/lines/blkstr.py
sldghmmr4nut/lines/fmt.py
sldghmmr4nut/ndarr/__init__.py
sldghmmr4nut/ndarr/convert.py
sldghmmr4nut/ndarr/do.py
sldghmmr4nut/zone/__init__.py
sldghmmr4nut/zone/const.py
sldghmmr4nut/zone/desc.py
sldghmmr4nut/zone/locs.py